archetypon/__init__.py
archetypon/_modidx.py
archetypon/base_model.py
archetypon/core.py
archetypon/database.py
archetypon/delegates.py
archetypon/formatting.py
archetypon/record_validation.py
archetypon/string_templating.py
archetypon-0.0.2.dist-info/LICENSE
archetypon-0.0.2.dist-info/METADATA
archetypon-0.0.2.dist-info/WHEEL
archetypon-0.0.2.dist-info/entry_points.txt
archetypon-0.0.2.dist-info/top_level.txt
archetypon-0.0.2.dist-info/RECORD
